discord_package/__init__.py
discord_package/cli.py
discord_package-0.0.5.dist-info/METADATA
discord_package-0.0.5.dist-info/WHEEL
discord_package-0.0.5.dist-info/entry_points.txt
discord_package-0.0.5.dist-info/top_level.txt
discord_package-0.0.5.dist-info/RECORD
