Metadata-Version: 2.1
Name: discord-package
Version: 0.0.5
Summary: A packager to create Discord bots easily
Home-page: https://github.com/MrWiki15/discord-package
Author: Polaris Web3
Author-email: universe@polarisweb3.org
Classifier: Programming Language :: Python :: 3
Classifier: License :: OSI Approved :: MIT License
Classifier: Operating System :: OS Independent
Requires-Python: >=3.6
Requires-Dist: discord.py
Requires-Dist: watchdog
Requires-Dist: asyncio
Requires-Dist: datetime
Requires-Dist: requests
Requires-Dist: rich
